Metadata-Version: 2.1
Name: pybwtool
Version: 1.0.3
Summary: Python wrapper for the bwtool library.
Home-page: https://github.com/LucaCappelletti94/pybwtool
Author: Luca Cappelletti
Author-email: cappelletti.luca94@gmail.com
License: MIT
Platform: UNKNOWN
Classifier: Development Status :: 3 - Alpha
Classifier: License :: OSI Approved :: MIT License
Classifier: Programming Language :: Python :: 3
Provides-Extra: test
